accuracy/__init__.py
accuracy/__main__.py
accuracy/_charts.py
accuracy/templates/template.html
tests/__init__.py
tests/prepare.py
tests/test_cli.py
accuracy-0.1.1.dist-info/METADATA
accuracy-0.1.1.dist-info/WHEEL
accuracy-0.1.1.dist-info/top_level.txt
accuracy-0.1.1.dist-info/RECORD
