Metadata-Version: 2.1
Name: accuracy
Version: 0.1.1
Summary: It's pronounced accura-see. For spaCy models.
Home-page: https://koaning.github.io/accuracy/
Author: Vincent D. Warmerdam
License: UNKNOWN
Project-URL: Documentation, https://koaning.github.io/accuracy/
Project-URL: Source Code, https://github.com/koaning/accuracy/
Project-URL: Issue Tracker, https://github.com/koaning/accuracy/issues
Platform: UNKNOWN
Classifier: Intended Audience :: Science/Research
Classifier: Programming Language :: Python :: 3
Classifier: Programming Language :: Python :: 3.7
Classifier: Programming Language :: Python :: 3.8
Classifier: Programming Language :: Python :: 3.9
Classifier: License :: OSI Approved :: MIT License
Classifier: Topic :: Scientific/Engineering
Classifier: Topic :: Scientific/Engineering :: Artificial Intelligence
Requires-Dist: Jinja2 (>=3.1.1)
Requires-Dist: altair (>=4.2.0)
Requires-Dist: clumper (>=0.2.15)
Requires-Dist: rich (>=10.3.0)
Requires-Dist: scikit-learn (>=1.0.0)
Requires-Dist: spacy (>=3.0.0)
Requires-Dist: typer (>=0.3.0)
Provides-Extra: base
Requires-Dist: Jinja2 (>=3.1.1) ; extra == 'base'
Requires-Dist: altair (>=4.2.0) ; extra == 'base'
Requires-Dist: clumper (>=0.2.15) ; extra == 'base'
Requires-Dist: rich (>=10.3.0) ; extra == 'base'
Requires-Dist: scikit-learn (>=1.0.0) ; extra == 'base'
Requires-Dist: spacy (>=3.0.0) ; extra == 'base'
Requires-Dist: typer (>=0.3.0) ; extra == 'base'
Provides-Extra: dev
Requires-Dist: Jinja2 (>=3.1.1) ; extra == 'dev'
Requires-Dist: altair (>=4.2.0) ; extra == 'dev'
Requires-Dist: black (>=21.0.0) ; extra == 'dev'
Requires-Dist: clumper (>=0.2.15) ; extra == 'dev'
Requires-Dist: flake8 (>=3.6.0) ; extra == 'dev'
Requires-Dist: interrogate (>=1.5.0) ; extra == 'dev'
Requires-Dist: pre-commit (>=2.17.0) ; extra == 'dev'
Requires-Dist: pytest (>=4.0.2) ; extra == 'dev'
Requires-Dist: rich (>=10.3.0) ; extra == 'dev'
Requires-Dist: scikit-learn (>=1.0.0) ; extra == 'dev'
Requires-Dist: spacy (>=3.0.0) ; extra == 'dev'
Requires-Dist: typer (>=0.3.0) ; extra == 'dev'
